odoo/addons/stock_brand/README.rst
odoo/addons/stock_brand/__init__.py
odoo/addons/stock_brand/__manifest__.py
odoo/addons/stock_brand/i18n/it.po
odoo/addons/stock_brand/i18n/nl.po
odoo/addons/stock_brand/i18n/stock_brand.pot
odoo/addons/stock_brand/models/__init__.py
odoo/addons/stock_brand/models/sale_order.py
odoo/addons/stock_brand/models/stock_picking.py
odoo/addons/stock_brand/readme/CONTRIBUTORS.md
odoo/addons/stock_brand/readme/CREDITS.md
odoo/addons/stock_brand/readme/DESCRIPTION.md
odoo/addons/stock_brand/readme/USAGE.md
odoo/addons/stock_brand/static/description/icon.png
odoo/addons/stock_brand/static/description/index.html
odoo/addons/stock_brand/tests/__init__.py
odoo/addons/stock_brand/tests/test_sale_order.py
odoo/addons/stock_brand/views/stock_picking_views.xml
odoo_addon_stock_brand-18.0.1.0.0.11.dist-info/METADATA
odoo_addon_stock_brand-18.0.1.0.0.11.dist-info/WHEEL
odoo_addon_stock_brand-18.0.1.0.0.11.dist-info/top_level.txt
odoo_addon_stock_brand-18.0.1.0.0.11.dist-info/RECORD
