Metadata-Version: 2.1
Name: odoo-addon-stock_brand
Version: 18.0.1.0.0.11
Requires-Python: >=3.10
Requires-Dist: odoo-addon-sale_brand==18.0.*
Requires-Dist: odoo==18.0.*
Summary: Manage brands on stock picking documents
Home-page: https://github.com/OCA/brand
License: AGPL-3
Author: Sunflower IT, Odoo Community Association (OCA)
Author-email: support@odoo-community.org
Classifier: Programming Language :: Python
Classifier: Framework :: Odoo
Classifier: Framework :: Odoo :: 18.0
Classifier: License :: OSI Approved :: GNU Affero General Public License v3
Classifier: Development Status :: 4 - Beta
